{
  "Player": {
    "ID": 14004,
    "Name": "sdfgjuytfds"
  },
  "Opponent": {
    "ID": 1002,
    "Name": "Knight"
  },
  "Result": "win",
  "IsPvp": false,
  "Rounds": [
    {
      "Number": 1,
      "Attacker": {
        "Name": "sdfgjuytfds",
        "HP": 696,
        "Crit": false,
        "Miss": false,
        "Damage": 63
      },
      "Defender": {
        "Name": "Knight",
        "HP": 573,
        "Block": true,
        "Receive": 27
      }
    },
    {
      "Number": 1,
      "Attacker": {
        "Name": "Knight",
        "HP": 573,
        "Crit": false,
        "Miss": false,
        "Damage": 43
      },
      "Defender": {
        "Name": "sdfgjuytfds",
        "HP": 655,
        "Block": false,
        "Receive": 41
      }
    },
    {
      "Number": 2,
      "Attacker": {
        "Name": "sdfgjuytfds",
        "HP": 655,
        "Crit": false,
        "Miss": false,
        "Damage": 52
      },
      "Defender": {
        "Name": "Knight",
        "HP": 527,
        "Block": false,
        "Receive": 46
      }
    },
    {
      "Number": 2,
      "Attacker": {
        "Name": "Knight",
        "HP": 527,
        "Crit": false,
        "Miss": false,
        "Damage": 44
      },
      "Defender": {
        "Name": "sdfgjuytfds",
        "HP": 613,
        "Block": false,
        "Receive": 42
      }
    },
    {
      "Number": 3,
      "Attacker": {
        "Name": "sdfgjuytfds",
        "HP": 613,
        "Crit": false,
        "Miss": false,
        "Damage": 66
      },
      "Defender": {
        "Name": "Knight",
        "HP": 469,
        "Block": false,
        "Receive": 58
      }
    },
    {
      "Number": 3,
      "Attacker": {
        "Name": "Knight",
        "HP": 469,
        "Crit": false,
        "Miss": false,
        "Damage": 40
      },
      "Defender": {
        "Name": "sdfgjuytfds",
        "HP": 575,
        "Block": false,
        "Receive": 38
      }
    },
    {
      "Number": 4,
      "Attacker": {
        "Name": "sdfgjuytfds",
        "HP": 575,
        "Crit": false,
        "Miss": false,
        "Damage": 63
      },
      "Defender": {
        "Name": "Knight",
        "HP": 442,
        "Block": true,
        "Receive": 27
      }
    },
    {
      "Number": 4,
      "Attacker": {
        "Name": "Knight",
        "HP": 442,
        "Crit": false,
        "Miss": false,
        "Damage": 39
      },
      "Defender": {
        "Name": "sdfgjuytfds",
        "HP": 538,
        "Block": false,
        "Receive": 37
      }
    },
    {
      "Number": 5,
      "Attacker": {
        "Name": "sdfgjuytfds",
        "HP": 538,
        "Crit": false,
        "Miss": false,
        "Damage": 65
      },
      "Defender": {
        "Name": "Knight",
        "HP": 385,
        "Block": false,
        "Receive": 57
      }
    },
    {
      "Number": 5,
      "Attacker": {
        "Name": "Knight",
        "HP": 385,
        "Crit": false,
        "Miss": true,
        "Damage": 41
      },
      "Defender": {
        "Name": "sdfgjuytfds",
        "HP": 538,
        "Block": false,
        "Receive": 0
      }
    },
    {
      "Number": 6,
      "Attacker": {
        "Name": "sdfgjuytfds",
        "HP": 538,
        "Crit": false,
        "Miss": false,
        "Damage": 53
      },
      "Defender": {
        "Name": "Knight",
        "HP": 362,
        "Block": true,
        "Receive": 23
      }
    },
    {
      "Number": 6,
      "Attacker": {
        "Name": "Knight",
        "HP": 362,
        "Crit": false,
        "Miss": false,
        "Damage": 44
      },
      "Defender": {
        "Name": "sdfgjuytfds",
        "HP": 496,
        "Block": false,
        "Receive": 42
      }
    },
    {
      "Number": 7,
      "Attacker": {
        "Name": "sdfgjuytfds",
        "HP": 496,
        "Crit": false,
        "Miss": false,
        "Damage": 59
      },
      "Defender": {
        "Name": "Knight",
        "HP": 336,
        "Block": true,
        "Receive": 26
      }
    },
    {
      "Number": 7,
      "Attacker": {
        "Name": "Knight",
        "HP": 336,
        "Crit": false,
        "Miss": false,
        "Damage": 38
      },
      "Defender": {
        "Name": "sdfgjuytfds",
        "HP": 460,
        "Block": false,
        "Receive": 36
      }
    },
    {
      "Number": 8,
      "Attacker": {
        "Name": "sdfgjuytfds",
        "HP": 460,
        "Crit": false,
        "Miss": false,
        "Damage": 61
      },
      "Defender": {
        "Name": "Knight",
        "HP": 282,
        "Block": false,
        "Receive": 54
      }
    },
    {
      "Number": 8,
      "Attacker": {
        "Name": "Knight",
        "HP": 282,
        "Crit": false,
        "Miss": false,
        "Damage": 38
      },
      "Defender": {
        "Name": "sdfgjuytfds",
        "HP": 424,
        "Block": false,
        "Receive": 36
      }
    },
    {
      "Number": 9,
      "Attacker": {
        "Name": "sdfgjuytfds",
        "HP": 424,
        "Crit": false,
        "Miss": true,
        "Damage": 62
      },
      "Defender": {
        "Name": "Knight",
        "HP": 282,
        "Block": false,
        "Receive": 0
      }
    },
    {
      "Number": 9,
      "Attacker": {
        "Name": "Knight",
        "HP": 282,
        "Crit": false,
        "Miss": false,
        "Damage": 43
      },
      "Defender": {
        "Name": "sdfgjuytfds",
        "HP": 383,
        "Block": false,
        "Receive": 41
      }
    },
    {
      "Number": 10,
      "Attacker": {
        "Name": "sdfgjuytfds",
        "HP": 383,
        "Crit": false,
        "Miss": true,
        "Damage": 54
      },
      "Defender": {
        "Name": "Knight",
        "HP": 282,
        "Block": false,
        "Receive": 0
      }
    },
    {
      "Number": 10,
      "Attacker": {
        "Name": "Knight",
        "HP": 282,
        "Crit": false,
        "Miss": false,
        "Damage": 41
      },
      "Defender": {
        "Name": "sdfgjuytfds",
        "HP": 344,
        "Block": false,
        "Receive": 39
      }
    },
    {
      "Number": 11,
      "Attacker": {
        "Name": "sdfgjuytfds",
        "HP": 344,
        "Crit": false,
        "Miss": false,
        "Damage": 51
      },
      "Defender": {
        "Name": "Knight",
        "HP": 237,
        "Block": false,
        "Receive": 45
      }
    },
    {
      "Number": 11,
      "Attacker": {
        "Name": "Knight",
        "HP": 237,
        "Crit": false,
        "Miss": false,
        "Damage": 38
      },
      "Defender": {
        "Name": "sdfgjuytfds",
        "HP": 326,
        "Block": true,
        "Receive": 18
      }
    },
    {
      "Number": 12,
      "Attacker": {
        "Name": "sdfgjuytfds",
        "HP": 326,
        "Crit": false,
        "Miss": false,
        "Damage": 48
      },
      "Defender": {
        "Name": "Knight",
        "HP": 195,
        "Block": false,
        "Receive": 42
      }
    },
    {
      "Number": 12,
      "Attacker": {
        "Name": "Knight",
        "HP": 195,
        "Crit": false,
        "Miss": false,
        "Damage": 44
      },
      "Defender": {
        "Name": "sdfgjuytfds",
        "HP": 284,
        "Block": false,
        "Receive": 42
      }
    },
    {
      "Number": 13,
      "Attacker": {
        "Name": "sdfgjuytfds",
        "HP": 284,
        "Crit": false,
        "Miss": false,
        "Damage": 49
      },
      "Defender": {
        "Name": "Knight",
        "HP": 174,
        "Block": true,
        "Receive": 21
      }
    },
    {
      "Number": 13,
      "Attacker": {
        "Name": "Knight",
        "HP": 174,
        "Crit": false,
        "Miss": false,
        "Damage": 38
      },
      "Defender": {
        "Name": "sdfgjuytfds",
        "HP": 248,
        "Block": false,
        "Receive": 36
      }
    },
    {
      "Number": 14,
      "Attacker": {
        "Name": "sdfgjuytfds",
        "HP": 248,
        "Crit": false,
        "Miss": false,
        "Damage": 55
      },
      "Defender": {
        "Name": "Knight",
        "HP": 126,
        "Block": false,
        "Receive": 48
      }
    },
    {
      "Number": 14,
      "Attacker": {
        "Name": "Knight",
        "HP": 126,
        "Crit": false,
        "Miss": false,
        "Damage": 40
      },
      "Defender": {
        "Name": "sdfgjuytfds",
        "HP": 210,
        "Block": false,
        "Receive": 38
      }
    },
    {
      "Number": 15,
      "Attacker": {
        "Name": "sdfgjuytfds",
        "HP": 210,
        "Crit": false,
        "Miss": false,
        "Damage": 64
      },
      "Defender": {
        "Name": "Knight",
        "HP": 70,
        "Block": false,
        "Receive": 56
      }
    },
    {
      "Number": 15,
      "Attacker": {
        "Name": "Knight",
        "HP": 70,
        "Crit": false,
        "Miss": true,
        "Damage": 44
      },
      "Defender": {
        "Name": "sdfgjuytfds",
        "HP": 210,
        "Block": false,
        "Receive": 0
      }
    },
    {
      "Number": 16,
      "Attacker": {
        "Name": "sdfgjuytfds",
        "HP": 210,
        "Crit": false,
        "Miss": false,
        "Damage": 52
      },
      "Defender": {
        "Name": "Knight",
        "HP": 47,
        "Block": true,
        "Receive": 23
      }
    },
    {
      "Number": 16,
      "Attacker": {
        "Name": "Knight",
        "HP": 47,
        "Crit": false,
        "Miss": false,
        "Damage": 44
      },
      "Defender": {
        "Name": "sdfgjuytfds",
        "HP": 168,
        "Block": false,
        "Receive": 42
      }
    },
    {
      "Number": 17,
      "Attacker": {
        "Name": "sdfgjuytfds",
        "HP": 168,
        "Crit": false,
        "Miss": false,
        "Damage": 49
      },
      "Defender": {
        "Name": "Knight",
        "HP": 4,
        "Block": false,
        "Receive": 43
      }
    },
    {
      "Number": 17,
      "Attacker": {
        "Name": "Knight",
        "HP": 4,
        "Crit": false,
        "Miss": false,
        "Damage": 36
      },
      "Defender": {
        "Name": "sdfgjuytfds",
        "HP": 134,
        "Block": false,
        "Receive": 34
      }
    },
    {
      "Number": 18,
      "Attacker": {
        "Name": "sdfgjuytfds",
        "HP": 134,
        "Crit": false,
        "Miss": false,
        "Damage": 62
      },
      "Defender": {
        "Name": "Knight",
        "HP": -23,
        "Block": true,
        "Receive": 27
      }
    }
  ],
  "QuickFight": true,
  "Reward": {
    "Experience": 10,
    "Gold": 3,
    "ItemID": -1,
    "ItemName": null,
    "ItemRarity": null
  }
}