{
  "Player": {
    "ID": 16006,
    "Name": "Bree"
  },
  "Opponent": {
    "ID": 2003,
    "Name": "Werewolf"
  },
  "Result": "win",
  "IsPvp": false,
  "Rounds": [
    {
      "Number": 1,
      "Attacker": {
        "Name": "Bree",
        "HP": 1346,
        "Crit": false,
        "Miss": false,
        "Damage": 131
      },
      "Defender": {
        "Name": "Werewolf",
        "HP": 1177,
        "Block": false,
        "Receive": 123
      }
    },
    {
      "Number": 1,
      "Attacker": {
        "Name": "Werewolf",
        "HP": 1177,
        "Crit": false,
        "Miss": false,
        "Damage": 123
      },
      "Defender": {
        "Name": "Bree",
        "HP": 1231,
        "Block": false,
        "Receive": 115
      }
    },
    {
      "Number": 2,
      "Attacker": {
        "Name": "Bree",
        "HP": 1231,
        "Crit": true,
        "Miss": false,
        "Damage": 204
      },
      "Defender": {
        "Name": "Werewolf",
        "HP": 986,
        "Block": false,
        "Receive": 191
      }
    },
    {
      "Number": 2,
      "Attacker": {
        "Name": "Werewolf",
        "HP": 986,
        "Crit": false,
        "Miss": false,
        "Damage": 125
      },
      "Defender": {
        "Name": "Bree",
        "HP": 1114,
        "Block": false,
        "Receive": 117
      }
    },
    {
      "Number": 3,
      "Attacker": {
        "Name": "Bree",
        "HP": 1114,
        "Crit": false,
        "Miss": false,
        "Damage": 104
      },
      "Defender": {
        "Name": "Werewolf",
        "HP": 889,
        "Block": false,
        "Receive": 97
      }
    },
    {
      "Number": 3,
      "Attacker": {
        "Name": "Werewolf",
        "HP": 889,
        "Crit": false,
        "Miss": false,
        "Damage": 120
      },
      "Defender": {
        "Name": "Bree",
        "HP": 1058,
        "Block": true,
        "Receive": 56
      }
    },
    {
      "Number": 4,
      "Attacker": {
        "Name": "Bree",
        "HP": 1058,
        "Crit": true,
        "Miss": false,
        "Damage": 208
      },
      "Defender": {
        "Name": "Werewolf",
        "HP": 694,
        "Block": false,
        "Receive": 195
      }
    },
    {
      "Number": 4,
      "Attacker": {
        "Name": "Werewolf",
        "HP": 694,
        "Crit": false,
        "Miss": false,
        "Damage": 138
      },
      "Defender": {
        "Name": "Bree",
        "HP": 929,
        "Block": false,
        "Receive": 129
      }
    },
    {
      "Number": 5,
      "Attacker": {
        "Name": "Bree",
        "HP": 929,
        "Crit": true,
        "Miss": false,
        "Damage": 205
      },
      "Defender": {
        "Name": "Werewolf",
        "HP": 502,
        "Block": false,
        "Receive": 192
      }
    },
    {
      "Number": 5,
      "Attacker": {
        "Name": "Werewolf",
        "HP": 502,
        "Crit": true,
        "Miss": false,
        "Damage": 192
      },
      "Defender": {
        "Name": "Bree",
        "HP": 749,
        "Block": false,
        "Receive": 180
      }
    },
    {
      "Number": 6,
      "Attacker": {
        "Name": "Bree",
        "HP": 749,
        "Crit": false,
        "Miss": false,
        "Damage": 112
      },
      "Defender": {
        "Name": "Werewolf",
        "HP": 397,
        "Block": false,
        "Receive": 105
      }
    },
    {
      "Number": 6,
      "Attacker": {
        "Name": "Werewolf",
        "HP": 397,
        "Crit": false,
        "Miss": false,
        "Damage": 125
      },
      "Defender": {
        "Name": "Bree",
        "HP": 632,
        "Block": false,
        "Receive": 117
      }
    },
    {
      "Number": 7,
      "Attacker": {
        "Name": "Bree",
        "HP": 632,
        "Crit": false,
        "Miss": false,
        "Damage": 120
      },
      "Defender": {
        "Name": "Werewolf",
        "HP": 285,
        "Block": false,
        "Receive": 112
      }
    },
    {
      "Number": 7,
      "Attacker": {
        "Name": "Werewolf",
        "HP": 285,
        "Crit": false,
        "Miss": false,
        "Damage": 134
      },
      "Defender": {
        "Name": "Bree",
        "HP": 506,
        "Block": false,
        "Receive": 126
      }
    },
    {
      "Number": 8,
      "Attacker": {
        "Name": "Bree",
        "HP": 506,
        "Crit": true,
        "Miss": false,
        "Damage": 207
      },
      "Defender": {
        "Name": "Werewolf",
        "HP": 91,
        "Block": false,
        "Receive": 194
      }
    },
    {
      "Number": 8,
      "Attacker": {
        "Name": "Werewolf",
        "HP": 91,
        "Crit": false,
        "Miss": false,
        "Damage": 133
      },
      "Defender": {
        "Name": "Bree",
        "HP": 381,
        "Block": false,
        "Receive": 125
      }
    },
    {
      "Number": 9,
      "Attacker": {
        "Name": "Bree",
        "HP": 381,
        "Crit": false,
        "Miss": false,
        "Damage": 106
      },
      "Defender": {
        "Name": "Werewolf",
        "HP": -8,
        "Block": false,
        "Receive": 99
      }
    }
  ],
  "QuickFight": true,
  "Reward": {
    "Experience": 25,
    "Gold": 7,
    "ItemID": 2015,
    "ItemName": "Wooden Buckler",
    "ItemRarity": "unique"
  }
}