{
  "Player": {
    "ID": 16006,
    "Name": "Bree"
  },
  "Opponent": {
    "ID": 1002,
    "Name": "Knight"
  },
  "Result": "win",
  "IsPvp": false,
  "Rounds": [
    {
      "Number": 1,
      "Attacker": {
        "Name": "Bree",
        "HP": 654,
        "Crit": false,
        "Miss": false,
        "Damage": 100
      },
      "Defender": {
        "Name": "Knight",
        "HP": 556,
        "Block": true,
        "Receive": 44
      }
    },
    {
      "Number": 1,
      "Attacker": {
        "Name": "Knight",
        "HP": 556,
        "Crit": false,
        "Miss": false,
        "Damage": 39
      },
      "Defender": {
        "Name": "Bree",
        "HP": 617,
        "Block": false,
        "Receive": 37
      }
    },
    {
      "Number": 2,
      "Attacker": {
        "Name": "Bree",
        "HP": 617,
        "Crit": false,
        "Miss": false,
        "Damage": 105
      },
      "Defender": {
        "Name": "Knight",
        "HP": 463,
        "Block": false,
        "Receive": 93
      }
    },
    {
      "Number": 2,
      "Attacker": {
        "Name": "Knight",
        "HP": 463,
        "Crit": false,
        "Miss": false,
        "Damage": 36
      },
      "Defender": {
        "Name": "Bree",
        "HP": 583,
        "Block": false,
        "Receive": 34
      }
    },
    {
      "Number": 3,
      "Attacker": {
        "Name": "Bree",
        "HP": 583,
        "Crit": false,
        "Miss": false,
        "Damage": 91
      },
      "Defender": {
        "Name": "Knight",
        "HP": 383,
        "Block": false,
        "Receive": 80
      }
    },
    {
      "Number": 3,
      "Attacker": {
        "Name": "Bree",
        "HP": 583,
        "Crit": false,
        "Miss": false,
        "Damage": 117
      },
      "Defender": {
        "Name": "Knight",
        "HP": 280,
        "Block": false,
        "Receive": 103
      }
    },
    {
      "Number": 4,
      "Attacker": {
        "Name": "Knight",
        "HP": 280,
        "Crit": false,
        "Miss": false,
        "Damage": 44
      },
      "Defender": {
        "Name": "Bree",
        "HP": 541,
        "Block": false,
        "Receive": 42
      }
    },
    {
      "Number": 4,
      "Attacker": {
        "Name": "Bree",
        "HP": 541,
        "Crit": false,
        "Miss": false,
        "Damage": 105
      },
      "Defender": {
        "Name": "Knight",
        "HP": 234,
        "Block": true,
        "Receive": 46
      }
    },
    {
      "Number": 5,
      "Attacker": {
        "Name": "Knight",
        "HP": 234,
        "Crit": false,
        "Miss": false,
        "Damage": 42
      },
      "Defender": {
        "Name": "Bree",
        "HP": 501,
        "Block": false,
        "Receive": 40
      }
    },
    {
      "Number": 5,
      "Attacker": {
        "Name": "Bree",
        "HP": 501,
        "Crit": false,
        "Miss": false,
        "Damage": 107
      },
      "Defender": {
        "Name": "Knight",
        "HP": 139,
        "Block": false,
        "Receive": 95
      }
    },
    {
      "Number": 6,
      "Attacker": {
        "Name": "Knight",
        "HP": 139,
        "Crit": false,
        "Miss": false,
        "Damage": 38
      },
      "Defender": {
        "Name": "Bree",
        "HP": 465,
        "Block": false,
        "Receive": 36
      }
    },
    {
      "Number": 6,
      "Attacker": {
        "Name": "Bree",
        "HP": 465,
        "Crit": false,
        "Miss": true,
        "Damage": 92
      },
      "Defender": {
        "Name": "Knight",
        "HP": 139,
        "Block": true,
        "Receive": 0
      }
    },
    {
      "Number": 7,
      "Attacker": {
        "Name": "Bree",
        "HP": 465,
        "Crit": false,
        "Miss": false,
        "Damage": 112
      },
      "Defender": {
        "Name": "Knight",
        "HP": 40,
        "Block": false,
        "Receive": 99
      }
    },
    {
      "Number": 7,
      "Attacker": {
        "Name": "Knight",
        "HP": 40,
        "Crit": false,
        "Miss": false,
        "Damage": 41
      },
      "Defender": {
        "Name": "Bree",
        "HP": 426,
        "Block": false,
        "Receive": 39
      }
    },
    {
      "Number": 8,
      "Attacker": {
        "Name": "Bree",
        "HP": 426,
        "Crit": false,
        "Miss": false,
        "Damage": 106
      },
      "Defender": {
        "Name": "Knight",
        "HP": -54,
        "Block": false,
        "Receive": 94
      }
    }
  ],
  "QuickFight": true,
  "Reward": {
    "Experience": 10,
    "Gold": 3,
    "ItemID": 2,
    "ItemName": "Peasant boots",
    "ItemRarity": "normal"
  }
}