{
  "Player": {
    "ID": 13004,
    "Name": "Universe"
  },
  "Opponent": {
    "ID": 3,
    "Name": "Enchanted Tree"
  },
  "Result": "win",
  "IsPvp": false,
  "Rounds": [
    {
      "Number": 1,
      "Attacker": {
        "Name": "Universe",
        "HP": 218,
        "Crit": false,
        "Miss": false,
        "Damage": 25
      },
      "Defender": {
        "Name": "Enchanted Tree",
        "HP": 126,
        "Block": false,
        "Receive": 24
      }
    },
    {
      "Number": 1,
      "Attacker": {
        "Name": "Enchanted Tree",
        "HP": 126,
        "Crit": false,
        "Miss": false,
        "Damage": 6
      },
      "Defender": {
        "Name": "Universe",
        "HP": 213,
        "Block": false,
        "Receive": 5
      }
    },
    {
      "Number": 2,
      "Attacker": {
        "Name": "Universe",
        "HP": 213,
        "Crit": false,
        "Miss": false,
        "Damage": 27
      },
      "Defender": {
        "Name": "Enchanted Tree",
        "HP": 100,
        "Block": false,
        "Receive": 26
      }
    },
    {
      "Number": 2,
      "Attacker": {
        "Name": "Enchanted Tree",
        "HP": 100,
        "Crit": false,
        "Miss": true,
        "Damage": 8
      },
      "Defender": {
        "Name": "Universe",
        "HP": 213,
        "Block": false,
        "Receive": 0
      }
    },
    {
      "Number": 3,
      "Attacker": {
        "Name": "Universe",
        "HP": 213,
        "Crit": true,
        "Miss": false,
        "Damage": 39
      },
      "Defender": {
        "Name": "Enchanted Tree",
        "HP": 63,
        "Block": false,
        "Receive": 37
      }
    },
    {
      "Number": 3,
      "Attacker": {
        "Name": "Enchanted Tree",
        "HP": 63,
        "Crit": false,
        "Miss": false,
        "Damage": 11
      },
      "Defender": {
        "Name": "Universe",
        "HP": 203,
        "Block": false,
        "Receive": 10
      }
    },
    {
      "Number": 4,
      "Attacker": {
        "Name": "Universe",
        "HP": 203,
        "Crit": false,
        "Miss": false,
        "Damage": 31
      },
      "Defender": {
        "Name": "Enchanted Tree",
        "HP": 33,
        "Block": false,
        "Receive": 30
      }
    },
    {
      "Number": 4,
      "Attacker": {
        "Name": "Enchanted Tree",
        "HP": 33,
        "Crit": false,
        "Miss": false,
        "Damage": 11
      },
      "Defender": {
        "Name": "Universe",
        "HP": 193,
        "Block": false,
        "Receive": 10
      }
    },
    {
      "Number": 5,
      "Attacker": {
        "Name": "Universe",
        "HP": 193,
        "Crit": false,
        "Miss": false,
        "Damage": 28
      },
      "Defender": {
        "Name": "Enchanted Tree",
        "HP": 6,
        "Block": false,
        "Receive": 27
      }
    },
    {
      "Number": 5,
      "Attacker": {
        "Name": "Enchanted Tree",
        "HP": 6,
        "Crit": false,
        "Miss": true,
        "Damage": 6
      },
      "Defender": {
        "Name": "Universe",
        "HP": 193,
        "Block": false,
        "Receive": 0
      }
    },
    {
      "Number": 6,
      "Attacker": {
        "Name": "Universe",
        "HP": 193,
        "Crit": false,
        "Miss": false,
        "Damage": 26
      },
      "Defender": {
        "Name": "Enchanted Tree",
        "HP": -19,
        "Block": false,
        "Receive": 25
      }
    }
  ],
  "QuickFight": true,
  "Reward": {
    "Experience": 3,
    "Gold": 2,
    "ItemID": -1,
    "ItemName": null,
    "ItemRarity": null
  }
}