{
  "Player": {
    "ID": 13004,
    "Name": "Universe"
  },
  "Opponent": {
    "ID": 2002,
    "Name": "Mermaid"
  },
  "Result": "lose",
  "IsPvp": false,
  "Rounds": [
    {
      "Number": 1,
      "Attacker": {
        "Name": "Universe",
        "HP": 817,
        "Crit": false,
        "Miss": true,
        "Damage": 70
      },
      "Defender": {
        "Name": "Mermaid",
        "HP": 920,
        "Block": false,
        "Receive": 0
      }
    },
    {
      "Number": 1,
      "Attacker": {
        "Name": "Mermaid",
        "HP": 920,
        "Crit": false,
        "Miss": false,
        "Damage": 50
      },
      "Defender": {
        "Name": "Universe",
        "HP": 769,
        "Block": false,
        "Receive": 48
      }
    },
    {
      "Number": 2,
      "Attacker": {
        "Name": "Universe",
        "HP": 769,
        "Crit": false,
        "Miss": false,
        "Damage": 64
      },
      "Defender": {
        "Name": "Mermaid",
        "HP": 860,
        "Block": false,
        "Receive": 60
      }
    },
    {
      "Number": 2,
      "Attacker": {
        "Name": "Mermaid",
        "HP": 860,
        "Crit": false,
        "Miss": false,
        "Damage": 62
      },
      "Defender": {
        "Name": "Universe",
        "HP": 710,
        "Block": false,
        "Receive": 59
      }
    },
    {
      "Number": 3,
      "Attacker": {
        "Name": "Universe",
        "HP": 710,
        "Crit": false,
        "Miss": false,
        "Damage": 60
      },
      "Defender": {
        "Name": "Mermaid",
        "HP": 804,
        "Block": false,
        "Receive": 56
      }
    },
    {
      "Number": 3,
      "Attacker": {
        "Name": "Mermaid",
        "HP": 804,
        "Crit": false,
        "Miss": false,
        "Damage": 56
      },
      "Defender": {
        "Name": "Universe",
        "HP": 684,
        "Block": true,
        "Receive": 26
      }
    },
    {
      "Number": 4,
      "Attacker": {
        "Name": "Universe",
        "HP": 684,
        "Crit": false,
        "Miss": true,
        "Damage": 71
      },
      "Defender": {
        "Name": "Mermaid",
        "HP": 804,
        "Block": false,
        "Receive": 0
      }
    },
    {
      "Number": 4,
      "Attacker": {
        "Name": "Mermaid",
        "HP": 804,
        "Crit": false,
        "Miss": false,
        "Damage": 64
      },
      "Defender": {
        "Name": "Universe",
        "HP": 623,
        "Block": false,
        "Receive": 61
      }
    },
    {
      "Number": 5,
      "Attacker": {
        "Name": "Universe",
        "HP": 623,
        "Crit": false,
        "Miss": false,
        "Damage": 54
      },
      "Defender": {
        "Name": "Mermaid",
        "HP": 754,
        "Block": false,
        "Receive": 50
      }
    },
    {
      "Number": 5,
      "Attacker": {
        "Name": "Mermaid",
        "HP": 754,
        "Crit": false,
        "Miss": false,
        "Damage": 64
      },
      "Defender": {
        "Name": "Universe",
        "HP": 562,
        "Block": false,
        "Receive": 61
      }
    },
    {
      "Number": 6,
      "Attacker": {
        "Name": "Universe",
        "HP": 562,
        "Crit": false,
        "Miss": true,
        "Damage": 72
      },
      "Defender": {
        "Name": "Mermaid",
        "HP": 754,
        "Block": false,
        "Receive": 0
      }
    },
    {
      "Number": 6,
      "Attacker": {
        "Name": "Mermaid",
        "HP": 754,
        "Crit": false,
        "Miss": false,
        "Damage": 52
      },
      "Defender": {
        "Name": "Universe",
        "HP": 512,
        "Block": false,
        "Receive": 50
      }
    },
    {
      "Number": 7,
      "Attacker": {
        "Name": "Universe",
        "HP": 512,
        "Crit": false,
        "Miss": false,
        "Damage": 55
      },
      "Defender": {
        "Name": "Mermaid",
        "HP": 703,
        "Block": false,
        "Receive": 51
      }
    },
    {
      "Number": 7,
      "Attacker": {
        "Name": "Mermaid",
        "HP": 703,
        "Crit": false,
        "Miss": false,
        "Damage": 60
      },
      "Defender": {
        "Name": "Universe",
        "HP": 455,
        "Block": false,
        "Receive": 57
      }
    },
    {
      "Number": 8,
      "Attacker": {
        "Name": "Universe",
        "HP": 455,
        "Crit": false,
        "Miss": false,
        "Damage": 56
      },
      "Defender": {
        "Name": "Mermaid",
        "HP": 677,
        "Block": true,
        "Receive": 26
      }
    },
    {
      "Number": 8,
      "Attacker": {
        "Name": "Mermaid",
        "HP": 677,
        "Crit": false,
        "Miss": false,
        "Damage": 57
      },
      "Defender": {
        "Name": "Universe",
        "HP": 401,
        "Block": false,
        "Receive": 54
      }
    },
    {
      "Number": 9,
      "Attacker": {
        "Name": "Universe",
        "HP": 401,
        "Crit": false,
        "Miss": false,
        "Damage": 74
      },
      "Defender": {
        "Name": "Mermaid",
        "HP": 608,
        "Block": false,
        "Receive": 69
      }
    },
    {
      "Number": 9,
      "Attacker": {
        "Name": "Mermaid",
        "HP": 608,
        "Crit": false,
        "Miss": false,
        "Damage": 67
      },
      "Defender": {
        "Name": "Universe",
        "HP": 337,
        "Block": false,
        "Receive": 64
      }
    },
    {
      "Number": 10,
      "Attacker": {
        "Name": "Universe",
        "HP": 337,
        "Crit": false,
        "Miss": false,
        "Damage": 55
      },
      "Defender": {
        "Name": "Mermaid",
        "HP": 557,
        "Block": false,
        "Receive": 51
      }
    },
    {
      "Number": 10,
      "Attacker": {
        "Name": "Mermaid",
        "HP": 557,
        "Crit": false,
        "Miss": false,
        "Damage": 50
      },
      "Defender": {
        "Name": "Universe",
        "HP": 289,
        "Block": false,
        "Receive": 48
      }
    },
    {
      "Number": 11,
      "Attacker": {
        "Name": "Universe",
        "HP": 289,
        "Crit": false,
        "Miss": true,
        "Damage": 64
      },
      "Defender": {
        "Name": "Mermaid",
        "HP": 557,
        "Block": false,
        "Receive": 0
      }
    },
    {
      "Number": 11,
      "Attacker": {
        "Name": "Mermaid",
        "HP": 557,
        "Crit": false,
        "Miss": false,
        "Damage": 59
      },
      "Defender": {
        "Name": "Universe",
        "HP": 233,
        "Block": false,
        "Receive": 56
      }
    },
    {
      "Number": 12,
      "Attacker": {
        "Name": "Universe",
        "HP": 233,
        "Crit": false,
        "Miss": false,
        "Damage": 57
      },
      "Defender": {
        "Name": "Mermaid",
        "HP": 504,
        "Block": false,
        "Receive": 53
      }
    },
    {
      "Number": 12,
      "Attacker": {
        "Name": "Mermaid",
        "HP": 504,
        "Crit": false,
        "Miss": false,
        "Damage": 67
      },
      "Defender": {
        "Name": "Universe",
        "HP": 169,
        "Block": false,
        "Receive": 64
      }
    },
    {
      "Number": 13,
      "Attacker": {
        "Name": "Universe",
        "HP": 169,
        "Crit": false,
        "Miss": false,
        "Damage": 73
      },
      "Defender": {
        "Name": "Mermaid",
        "HP": 436,
        "Block": false,
        "Receive": 68
      }
    },
    {
      "Number": 13,
      "Attacker": {
        "Name": "Mermaid",
        "HP": 436,
        "Crit": false,
        "Miss": true,
        "Damage": 53
      },
      "Defender": {
        "Name": "Universe",
        "HP": 169,
        "Block": false,
        "Receive": 0
      }
    },
    {
      "Number": 14,
      "Attacker": {
        "Name": "Universe",
        "HP": 169,
        "Crit": false,
        "Miss": false,
        "Damage": 65
      },
      "Defender": {
        "Name": "Mermaid",
        "HP": 406,
        "Block": true,
        "Receive": 30
      }
    },
    {
      "Number": 14,
      "Attacker": {
        "Name": "Mermaid",
        "HP": 406,
        "Crit": false,
        "Miss": false,
        "Damage": 67
      },
      "Defender": {
        "Name": "Universe",
        "HP": 105,
        "Block": false,
        "Receive": 64
      }
    },
    {
      "Number": 15,
      "Attacker": {
        "Name": "Universe",
        "HP": 105,
        "Crit": false,
        "Miss": true,
        "Damage": 59
      },
      "Defender": {
        "Name": "Mermaid",
        "HP": 406,
        "Block": false,
        "Receive": 0
      }
    },
    {
      "Number": 15,
      "Attacker": {
        "Name": "Mermaid",
        "HP": 406,
        "Crit": false,
        "Miss": false,
        "Damage": 58
      },
      "Defender": {
        "Name": "Universe",
        "HP": 50,
        "Block": false,
        "Receive": 55
      }
    },
    {
      "Number": 16,
      "Attacker": {
        "Name": "Universe",
        "HP": 50,
        "Crit": false,
        "Miss": false,
        "Damage": 76
      },
      "Defender": {
        "Name": "Mermaid",
        "HP": 335,
        "Block": false,
        "Receive": 71
      }
    },
    {
      "Number": 16,
      "Attacker": {
        "Name": "Mermaid",
        "HP": 335,
        "Crit": false,
        "Miss": false,
        "Damage": 58
      },
      "Defender": {
        "Name": "Universe",
        "HP": -5,
        "Block": false,
        "Receive": 55
      }
    }
  ],
  "QuickFight": true,
  "Reward": {
    "Experience": 0,
    "Gold": 0,
    "ItemID": 0,
    "ItemName": null,
    "ItemRarity": null
  }
}