{
  "Player": {
    "ID": 11005,
    "Name": "Bason"
  },
  "Opponent": {
    "ID": 4,
    "Name": "Goblin"
  },
  "Result": "win",
  "IsPvp": false,
  "Rounds": [
    {
      "Number": 1,
      "Attacker": {
        "Name": "Goblin",
        "HP": 280,
        "Crit": false,
        "Miss": false,
        "Damage": 14
      },
      "Defender": {
        "Name": "Bason",
        "HP": 328,
        "Block": false,
        "Receive": 13
      }
    },
    {
      "Number": 1,
      "Attacker": {
        "Name": "Bason",
        "HP": 328,
        "Crit": false,
        "Miss": false,
        "Damage": 23
      },
      "Defender": {
        "Name": "Goblin",
        "HP": 257,
        "Block": false,
        "Receive": 23
      }
    },
    {
      "Number": 2,
      "Attacker": {
        "Name": "Goblin",
        "HP": 257,
        "Crit": false,
        "Miss": false,
        "Damage": 16
      },
      "Defender": {
        "Name": "Bason",
        "HP": 313,
        "Block": false,
        "Receive": 15
      }
    },
    {
      "Number": 2,
      "Attacker": {
        "Name": "Goblin",
        "HP": 257,
        "Crit": false,
        "Miss": false,
        "Damage": 17
      },
      "Defender": {
        "Name": "Bason",
        "HP": 297,
        "Block": false,
        "Receive": 16
      }
    },
    {
      "Number": 3,
      "Attacker": {
        "Name": "Bason",
        "HP": 297,
        "Crit": false,
        "Miss": false,
        "Damage": 23
      },
      "Defender": {
        "Name": "Goblin",
        "HP": 234,
        "Block": false,
        "Receive": 23
      }
    },
    {
      "Number": 3,
      "Attacker": {
        "Name": "Goblin",
        "HP": 234,
        "Crit": false,
        "Miss": false,
        "Damage": 18
      },
      "Defender": {
        "Name": "Bason",
        "HP": 280,
        "Block": false,
        "Receive": 17
      }
    },
    {
      "Number": 4,
      "Attacker": {
        "Name": "Bason",
        "HP": 280,
        "Crit": false,
        "Miss": false,
        "Damage": 20
      },
      "Defender": {
        "Name": "Goblin",
        "HP": 214,
        "Block": false,
        "Receive": 20
      }
    },
    {
      "Number": 4,
      "Attacker": {
        "Name": "Goblin",
        "HP": 214,
        "Crit": false,
        "Miss": false,
        "Damage": 14
      },
      "Defender": {
        "Name": "Bason",
        "HP": 267,
        "Block": false,
        "Receive": 13
      }
    },
    {
      "Number": 5,
      "Attacker": {
        "Name": "Bason",
        "HP": 267,
        "Crit": false,
        "Miss": false,
        "Damage": 21
      },
      "Defender": {
        "Name": "Goblin",
        "HP": 193,
        "Block": false,
        "Receive": 21
      }
    },
    {
      "Number": 5,
      "Attacker": {
        "Name": "Goblin",
        "HP": 193,
        "Crit": false,
        "Miss": false,
        "Damage": 15
      },
      "Defender": {
        "Name": "Bason",
        "HP": 253,
        "Block": false,
        "Receive": 14
      }
    },
    {
      "Number": 6,
      "Attacker": {
        "Name": "Goblin",
        "HP": 193,
        "Crit": false,
        "Miss": false,
        "Damage": 16
      },
      "Defender": {
        "Name": "Bason",
        "HP": 238,
        "Block": false,
        "Receive": 15
      }
    },
    {
      "Number": 6,
      "Attacker": {
        "Name": "Bason",
        "HP": 238,
        "Crit": false,
        "Miss": false,
        "Damage": 24
      },
      "Defender": {
        "Name": "Goblin",
        "HP": 169,
        "Block": false,
        "Receive": 24
      }
    },
    {
      "Number": 7,
      "Attacker": {
        "Name": "Goblin",
        "HP": 169,
        "Crit": false,
        "Miss": false,
        "Damage": 14
      },
      "Defender": {
        "Name": "Bason",
        "HP": 225,
        "Block": false,
        "Receive": 13
      }
    },
    {
      "Number": 7,
      "Attacker": {
        "Name": "Bason",
        "HP": 225,
        "Crit": false,
        "Miss": false,
        "Damage": 25
      },
      "Defender": {
        "Name": "Goblin",
        "HP": 144,
        "Block": false,
        "Receive": 25
      }
    },
    {
      "Number": 8,
      "Attacker": {
        "Name": "Goblin",
        "HP": 144,
        "Crit": false,
        "Miss": false,
        "Damage": 19
      },
      "Defender": {
        "Name": "Bason",
        "HP": 207,
        "Block": false,
        "Receive": 18
      }
    },
    {
      "Number": 8,
      "Attacker": {
        "Name": "Goblin",
        "HP": 144,
        "Crit": false,
        "Miss": false,
        "Damage": 17
      },
      "Defender": {
        "Name": "Bason",
        "HP": 191,
        "Block": false,
        "Receive": 16
      }
    },
    {
      "Number": 9,
      "Attacker": {
        "Name": "Bason",
        "HP": 191,
        "Crit": false,
        "Miss": false,
        "Damage": 25
      },
      "Defender": {
        "Name": "Goblin",
        "HP": 119,
        "Block": false,
        "Receive": 25
      }
    },
    {
      "Number": 9,
      "Attacker": {
        "Name": "Goblin",
        "HP": 119,
        "Crit": false,
        "Miss": false,
        "Damage": 17
      },
      "Defender": {
        "Name": "Bason",
        "HP": 175,
        "Block": false,
        "Receive": 16
      }
    },
    {
      "Number": 10,
      "Attacker": {
        "Name": "Bason",
        "HP": 175,
        "Crit": false,
        "Miss": false,
        "Damage": 25
      },
      "Defender": {
        "Name": "Goblin",
        "HP": 94,
        "Block": false,
        "Receive": 25
      }
    },
    {
      "Number": 10,
      "Attacker": {
        "Name": "Goblin",
        "HP": 94,
        "Crit": false,
        "Miss": false,
        "Damage": 17
      },
      "Defender": {
        "Name": "Bason",
        "HP": 159,
        "Block": false,
        "Receive": 16
      }
    },
    {
      "Number": 11,
      "Attacker": {
        "Name": "Bason",
        "HP": 159,
        "Crit": false,
        "Miss": false,
        "Damage": 23
      },
      "Defender": {
        "Name": "Goblin",
        "HP": 71,
        "Block": false,
        "Receive": 23
      }
    },
    {
      "Number": 11,
      "Attacker": {
        "Name": "Goblin",
        "HP": 71,
        "Crit": false,
        "Miss": false,
        "Damage": 19
      },
      "Defender": {
        "Name": "Bason",
        "HP": 141,
        "Block": false,
        "Receive": 18
      }
    },
    {
      "Number": 12,
      "Attacker": {
        "Name": "Goblin",
        "HP": 71,
        "Crit": false,
        "Miss": false,
        "Damage": 18
      },
      "Defender": {
        "Name": "Bason",
        "HP": 124,
        "Block": false,
        "Receive": 17
      }
    },
    {
      "Number": 12,
      "Attacker": {
        "Name": "Bason",
        "HP": 124,
        "Crit": false,
        "Miss": false,
        "Damage": 20
      },
      "Defender": {
        "Name": "Goblin",
        "HP": 51,
        "Block": false,
        "Receive": 20
      }
    },
    {
      "Number": 13,
      "Attacker": {
        "Name": "Goblin",
        "HP": 51,
        "Crit": false,
        "Miss": false,
        "Damage": 18
      },
      "Defender": {
        "Name": "Bason",
        "HP": 107,
        "Block": false,
        "Receive": 17
      }
    },
    {
      "Number": 13,
      "Attacker": {
        "Name": "Bason",
        "HP": 107,
        "Crit": false,
        "Miss": false,
        "Damage": 25
      },
      "Defender": {
        "Name": "Goblin",
        "HP": 26,
        "Block": false,
        "Receive": 25
      }
    },
    {
      "Number": 14,
      "Attacker": {
        "Name": "Goblin",
        "HP": 26,
        "Crit": false,
        "Miss": false,
        "Damage": 17
      },
      "Defender": {
        "Name": "Bason",
        "HP": 91,
        "Block": false,
        "Receive": 16
      }
    },
    {
      "Number": 14,
      "Attacker": {
        "Name": "Goblin",
        "HP": 26,
        "Crit": false,
        "Miss": false,
        "Damage": 16
      },
      "Defender": {
        "Name": "Bason",
        "HP": 76,
        "Block": false,
        "Receive": 15
      }
    },
    {
      "Number": 15,
      "Attacker": {
        "Name": "Bason",
        "HP": 76,
        "Crit": true,
        "Miss": false,
        "Damage": 34
      },
      "Defender": {
        "Name": "Goblin",
        "HP": -8,
        "Block": false,
        "Receive": 34
      }
    }
  ],
  "QuickFight": true,
  "Reward": {
    "Experience": 2,
    "Gold": 2,
    "ItemID": -1,
    "ItemName": null,
    "ItemRarity": null
  }
}